topsis/102216114.py
topsis/__init__.py
topsis_ANANYA_102216114-1.0.3.dist-info/LICENSE
topsis_ANANYA_102216114-1.0.3.dist-info/METADATA
topsis_ANANYA_102216114-1.0.3.dist-info/WHEEL
topsis_ANANYA_102216114-1.0.3.dist-info/entry_points.txt
topsis_ANANYA_102216114-1.0.3.dist-info/top_level.txt
topsis_ANANYA_102216114-1.0.3.dist-info/RECORD
