Metadata-Version: 2.1
Name: topsis-ANANYA-102216114
Version: 1.0.3
Summary: A Python package for performing TOPSIS (Technique for Order Preference by Similarity to Ideal Solution) to rank the entries in a dataset.
Home-page: https://github.com/ananyagr02/topsis-ANANYA-102216114
Author: Ananya Gaur
Author-email: hiananya02@gmail.com
Classifier: Programming Language :: Python :: 3
Classifier: License :: OSI Approved :: MIT License
Classifier: Operating System :: OS Independent
Classifier: Topic :: Scientific/Engineering
Classifier: Topic :: Scientific/Engineering :: Information Analysis
Classifier: Intended Audience :: Developers
Classifier: Intended Audience :: Science/Research
Requires-Python: >=3.7
License-File: LICENSE
Requires-Dist: numpy>=1.20.0
Requires-Dist: pandas>=1.3.0
Requires-Dist: scikit-learn>=0.24.0
